{"name":"dart:","dependencies":[],"fullVersion":"0.1.2.0_r23299_efortuna","revision":"23299","libraries":[{"refId":"args","name":"package:args/args.dart"},{"refId":"dart.async","name":"dart:async"},{"refId":"chrome","name":"dart:chrome"},{"refId":"dart.collection","name":"dart:collection"},{"refId":"dart.core","name":"dart:core"},{"refId":"dart.crypto","name":"dart:crypto"},{"refId":"dart.dom.html","name":"dart:html"},{"refId":"dart.dom.indexed_db","name":"dart:indexed_db"},{"refId":"dart.io","name":"dart:io"},{"refId":"dart.isolate","name":"dart:isolate"},{"refId":"dart.json","name":"dart:json"},{"refId":"dart.math","name":"dart:math"},{"refId":"dart.mirrors","name":"dart:mirrors"},{"refId":"dart.dom.svg","name":"dart:svg"},{"refId":"dart.typed_data","name":"dart:typed_data"},{"refId":"dart.utf","name":"dart:utf"},{"refId":"dart.dom.web_audio","name":"dart:web_audio"},{"refId":"dart.dom.web_gl","name":"dart:web_gl"},{"refId":"dart.dom.web_sql","name":"dart:web_sql"},{"refId":"fixnum","name":"package:fixnum/fixnum.dart"},{"refId":"intl","name":"package:intl/intl.dart"},{"refId":"logging","name":"package:logging/logging.dart"},{"refId":"matcher","name":"package:unittest/matcher.dart"},{"refId":"mdv_observe","name":"package:mdv_observe/mdv_observe.dart"},{"refId":"meta","name":"package:meta/meta.dart"},{"refId":"mock","name":"package:unittest/mock.dart"},{"refId":"serialization","name":"package:serialization/serialization.dart"},{"refId":"unittest","name":"package:unittest/unittest.dart"}],"description":"Dart System Libraries"}
